[
    {
      "id": 1,
      "name": "Ahnex Builders & Ready Mix Corp.",
      "contactPerson": "John Doe",
      "emailAddress": "john.doe@email.com",
      "contactNumber": "09123456789",
      "isActive": true
    },
    {
      "id": 2,
      "name": "Blue Horizon Metal Corp.",
      "contactPerson": "Mighty Blue",
      "emailAddress": "mighty.blue@email.com",
      "contactNumber": "09123456780",
      "isActive": true
    },
    {
      "id": 3,
      "name": "BradPhil Inc.",
      "contactPerson": "Brad Traversy",
      "emailAddress": "brad.traversy@email.com",
      "contactNumber": "09123456781",
      "isActive": false
    },
    {
      "id": 4,
      "name": "Bue Trucking Services",
      "contactPerson": "Sarah Lee",
      "emailAddress": "sarah.lee@email.com",
      "contactNumber": "09123456782",
      "isActive": true
    },
    {
      "id": 5,
      "name": "Citystar Hardware and Steel Supply",
      "contactPerson": "Jericho Lopez",
      "emailAddress": "jericho.lopez@email.com",
      "contactNumber": "09123456783",
      "isActive": true
    },
    {
      "id": 6,
      "name": "Christopher Metals Trading",
      "contactPerson": "Michelle R. Santos",
      "emailAddress": "michelle.santos@email.com",
      "contactNumber": "09123456784",
      "isActive": true
    },
    {
      "id": 7,
      "name": "CRF2 Enterprises",
      "contactPerson": "Christopher Feliciano",
      "emailAddress": "christopher.feliciano@email.com",
      "contactNumber": "09123456785",
      "isActive": true
    },
    {
      "id": 8,
      "name": "CS Bartolome Woods Scrap Trading",
      "contactPerson": "Baltazar Bartolome",
      "emailAddress": "baltazar.bartolome@email.com",
      "contactNumber": "09123456786",
      "isActive": true
    },
    {
      "id": 9,
      "name": "DAP Pipes Manufacturing",
      "contactPerson": "David Pau",
      "emailAddress": "david.pau@email.com",
      "contactNumber": "09123456787",
      "isActive": true
    }
  ]